{
  "lookback": 30,
  "stride": 1,
  "min_assets": 25,
  "min_valid_ratio": 1.0,
  "horizon": 0,
  "zero_as_invalid": false,
  "batch_size": 200,
  "epochs": 100,
  "lr": 0.001,
  "weight_decay": 0.0,
  "grad_clip": 1.0,
  "eval_interval": 1,
  "objective": "sharpe",
  "weight_scheme": "l1",
  "trans_cost": 0.0005,
  "hold_cost": 0.0001,
  "log_test": true,
  "cnn_channels": [32, 64, 64],
  "cnn_kernel_sizes": [3, 3, 3],
  "transformer_d_model": 64,
  "transformer_nhead": 4,
  "transformer_num_layers": 2,
  "device": "mps",
  "dtype": "float32"
}
